bogir/__init__.py
bogir/base_merchant_manager.py
bogir/everymatrix_merch_manager.py
bogir/merchant_factory.py
bogir/mima_merch_manager.py
bogir/schemas/__init__.py
bogir/schemas/everymatrix.py
bogir/schemas/mima.py
bogir-0.0.6.dist-info/METADATA
bogir-0.0.6.dist-info/WHEEL
bogir-0.0.6.dist-info/top_level.txt
bogir-0.0.6.dist-info/RECORD
