Metadata-Version: 2.1
Name: bogir
Version: 0.0.6
Author: Giorgi Khunashvili
Author-email: gkhunashvili@icloud.com
License: MIT
Classifier: Programming Language :: Python :: 3.11
Requires-Python: >=3.9.0
Requires-Dist: pyhumps ==3.8.0
Requires-Dist: requests ==2.28.1
